mmmeta/__init__.py
mmmeta/cli.py
mmmeta/config.py
mmmeta/db.py
mmmeta/exceptions.py
mmmeta/file.py
mmmeta/logging.py
mmmeta/metadir.py
mmmeta/settings.py
mmmeta/util.py
mmmeta/backend/__init__.py
mmmeta/backend/appendonly.py
mmmeta/backend/base.py
mmmeta/backend/filesystem.py
mmmeta/backend/store.py
mmmeta-0.4.4.dist-info/LICENSE
mmmeta-0.4.4.dist-info/METADATA
mmmeta-0.4.4.dist-info/WHEEL
mmmeta-0.4.4.dist-info/entry_points.txt
mmmeta-0.4.4.dist-info/top_level.txt
mmmeta-0.4.4.dist-info/RECORD
