Metadata-Version: 2.1
Name: mmmeta
Version: 0.4.4
Summary: A simple toolkit for managing local state against remote metadata.
Home-page: https://github.com/simonwoerpel/mmmeta
Author: Simon Wörpel
Author-email: simon.woerpel@medienrevolte.de
License: MIT
Platform: UNKNOWN
Classifier: Development Status :: 3 - Alpha
Classifier: Intended Audience :: Developers
Classifier: License :: OSI Approved :: MIT License
Classifier: Programming Language :: Python :: 3
Classifier: Topic :: Utilities
License-File: LICENSE
Requires-Dist: banal
Requires-Dist: click
Requires-Dist: dataset
Requires-Dist: python-dateutil
Requires-Dist: pyyaml
Requires-Dist: structlog
